README.txt
setup.py
monkey/__init__.py
monkey.egg-info/PKG-INFO
monkey.egg-info/SOURCES.txt
monkey.egg-info/dependency_links.txt
monkey.egg-info/entry_points.txt
monkey.egg-info/not-zip-safe
monkey.egg-info/top_level.txt
