Metadata-Version: 1.0
Name: monkey
Version: 0.1
Summary: A package that provides tools for guerilla (monkey)-patching.
Home-page: UNKNOWN
Author: Malthe Borch
Author-email: mborch@gmail.com
License: BSD
Platform: UNKNOWN
Classifier: Topic :: Software Development :: Quality Assurance
Classifier: License :: OSI Approved :: BSD License
Classifier: Programming Language :: Python
Classifier: Development Status :: 4 - Beta
Classifier: Topic :: Utilities
